modal_streamlit_vmateo/__init__.py
modal_streamlit_vmateo-0.0.1.dist-info/METADATA
modal_streamlit_vmateo-0.0.1.dist-info/WHEEL
modal_streamlit_vmateo-0.0.1.dist-info/top_level.txt
modal_streamlit_vmateo-0.0.1.dist-info/RECORD
